MANIFEST.in
README.rst
setup.py
aplist/__init__.py
aplist/aplist.py
aplist/data_provider.py
aplist/decoder.py
aplist/processor.py
aplist.egg-info/PKG-INFO
aplist.egg-info/SOURCES.txt
aplist.egg-info/dependency_links.txt
aplist.egg-info/not-zip-safe
aplist.egg-info/requires.txt
aplist.egg-info/top_level.txt