Metadata-Version: 1.1
Name: aplist
Version: 0.1.dev2
Summary: Airport List Query module
Home-page: https://github.com/MatthieuMichon/aplist
Author: Matthieu Michon
Author-email: matthieu.michon@gmail.com
License: GPLv3
Platform: UNKNOWN
Classifier: Development Status :: 3 - Alpha
Classifier: License :: OSI Approved :: MIT License
Classifier: Programming Language :: Python :: 3 :: Only
Classifier: Topic :: Scientific/Engineering
